docker_helper.py
ecs_helper.py
slack_api.py
commons/__init__.py
commons/config.py
commons/constant.py
printsid-0.1.data/scripts/dokr
utils/__init__.py
utils/helper.py
utils/http_client.py
utils/logger.py
printsid-0.1.dist-info/LICENSE
printsid-0.1.dist-info/METADATA
printsid-0.1.dist-info/WHEEL
printsid-0.1.dist-info/top_level.txt
printsid-0.1.dist-info/RECORD
