Metadata-Version: 2.1
Name: printsid
Version: 0.1
Summary: A dummy package
Home-page: UNKNOWN
Author: Siddharth Bhonge
Author-email: bsiddharth4@gmail.com
License: UNKNOWN
Platform: UNKNOWN
Classifier: Programming Language :: Python :: 3
Classifier: License :: OSI Approved :: MIT License
Classifier: Operating System :: OS Independent
Requires-Dist: requests
Requires-Dist: click
Requires-Dist: configparser
